pytest_docfiles/plugin.py
pytest_docfiles-0.2.0.dist-info/LICENSE
pytest_docfiles-0.2.0.dist-info/METADATA
pytest_docfiles-0.2.0.dist-info/WHEEL
pytest_docfiles-0.2.0.dist-info/entry_points.txt
pytest_docfiles-0.2.0.dist-info/top_level.txt
pytest_docfiles-0.2.0.dist-info/RECORD
