Metadata-Version: 2.1
Name: pytest-docfiles
Version: 0.2.0
Summary: pytest plugin to test codeblocks in your documentation.
Home-page: https://www.github.com/stefanhoelzl/pytest_docfiles/
Author: Stefan Hoelzl
Author-email: stefanh+pytest_docfiles@posteo.de
License: MIT
Keywords: pytest plugin markdown documentation codeblocks
Platform: UNKNOWN
Classifier: Development Status :: 4 - Beta
Classifier: Intended Audience :: Developers
Classifier: License :: OSI Approved :: MIT License
Classifier: Programming Language :: Python :: 3
Classifier: Programming Language :: Python :: 3.7
Classifier: Programming Language :: Python :: 3.8
Classifier: Programming Language :: Python :: 3.9
Classifier: Programming Language :: Python :: 3.10
Classifier: Operating System :: MacOS :: MacOS X
Classifier: Operating System :: POSIX :: Linux
Classifier: Operating System :: Microsoft :: Windows
Classifier: Topic :: Software Development
Classifier: Topic :: Software Development :: Testing
License-File: LICENSE
Requires-Dist: pytest (>=3.7.0)
Requires-Dist: markdown-it-py (>=2.0.0)
